20UAI039.jpeg
CHANGELOG.txt
MANIFEST.in
README.txt
__init__.py
license.txt
main.py
setup.py
nolan_eg.egg-info/PKG-INFO
nolan_eg.egg-info/SOURCES.txt
nolan_eg.egg-info/dependency_links.txt
nolan_eg.egg-info/top_level.txt