Metadata-Version: 1.1
Name: nolan-eg
Version: 0.0.1
Summary: A Testing library
Home-page: UNKNOWN
Author: ragul nolan
Author-email: slrk4444@gmail.com
License: MIT
Keywords: testing
Platform: UNKNOWN
Classifier: Development Status :: 5 - Production/Stable
Classifier: Intended Audience :: Other Audience
Classifier: Operating System :: Microsoft :: Windows :: Windows 10
Classifier: License :: OSI Approved :: MIT License
Classifier: Programming Language :: Python :: 3
